LICENSE
README.md
setup.py
multitoeter/__init__.py
multitoeter/autoinit.py
multitoeter/mastodon.py
multitoeter/twitter.py
multitoeter/unifiedapi.py
multitoeter.egg-info/PKG-INFO
multitoeter.egg-info/SOURCES.txt
multitoeter.egg-info/dependency_links.txt
multitoeter.egg-info/requires.txt
multitoeter.egg-info/top_level.txt