Metadata-Version: 2.1
Name: multitoeter
Version: 2
Summary: Send out messages to Mastodon and Twitter using one simplistic unified API
Home-page: https://github.com/Sikerdebaard/MultiToeter
Author: Thomas Phil
Author-email: thomas@tphil.nl
License: UNKNOWN
Platform: UNKNOWN
Requires-Python: >=3.7
License-File: LICENSE
